plain/elements/CHANGELOG.md
plain/elements/README.md
plain/elements/__init__.py
plain/elements/templates.py
plain_elements-0.10.2.dist-info/METADATA
plain_elements-0.10.2.dist-info/WHEEL
plain_elements-0.10.2.dist-info/licenses/LICENSE
plain_elements-0.10.2.dist-info/RECORD
