Metadata-Version: 2.4
Name: plain.elements
Version: 0.10.2
Summary: Use HTML tags to include HTML template components.
Author-email: Dave Gaeddert <dave.gaeddert@dropseed.dev>
License-File: LICENSE
Requires-Python: >=3.13
Requires-Dist: plain<1.0.0
